app/__init__.py
app/api.py
app/callbacks.py
app/file_operations.py
app/main.py
addcom-1.0.3.dist-info/entry_points.txt
addcom-1.0.3.dist-info/LICENSE
addcom-1.0.3.dist-info/METADATA
addcom-1.0.3.dist-info/WHEEL
addcom-1.0.3.dist-info/RECORD
