Metadata-Version: 2.1
Name: addcom
Version: 1.0.3
Summary: a CLI tool for adding comments to your source code files
Home-page: https://github.com/arilloid/addcom
License: MIT
Author: Arina Kolodeznikova
Author-email: arinak1017@gmail.com
Requires-Python: >=3.12,<4.0
Classifier: License :: OSI Approved :: MIT License
Classifier: Programming Language :: Python :: 3
Classifier: Programming Language :: Python :: 3.12
Requires-Dist: openai (>=1.46,<2.0)
Requires-Dist: rich (>=13.8,<14.0)
Requires-Dist: typer (>=0.12,<0.13)
Requires-Dist: typing_extensions (>=4.12,<5.0)
Project-URL: Repository, https://github.com/arilloid/addcom
